DAT/deserializer.v
module deserializer(
	clk, 		//serialized data proper clock
	enable, 	//suspend while enable on low
	reset, 		//set output to zero and reset counter to 0 on high
	framesize, 	//number of bits to be deserialized
	in, 		//serialized data
	out, 		//deserialized data
	complete	//reset counter to 0 and hold out's data while high
);

	parameter BITS = 32;		//size of deserializer
	parameter BITS_COUNTER = 8;	//size of counter, must be at least log2(BITS)

	input clk, enable, reset, in;
	input [BITS_COUNTER-1:0] framesize;

	output reg complete;
	output reg [BITS-1:0] out;
	reg [BITS_COUNTER-1:0] counter;	//we need to know which array item (out) to write on


	//always@(posedge clk) begin
	//if (reset==1'b1) begin
		//out <= 32'b00000000000000000000000000000000;
		//counter <= 8'b00000000;
		//complete <= 1'b0;
	//end


//	end

	always@(posedge clk) begin

	if (reset==1'b1) begin
		out <= 32'b00000000000000000000000000000000;
		counter <= 8'b00000000;
//		complete <= 1'b0;
	end
	else  begin
		if(enable) begin
	   if (complete==1'b0) begin


				out[counter] <= in;
				counter  <= counter + 1;	//next item
				 end
			end
			end
end

always @ ( * ) begin
	if (counter==framesize) begin
		complete=1'b1;
		end
		else begin
complete=1'b0;
		end
end


	//always@(complete) begin
		//counter  = 0;	//this way there's no need to reset every time we start a transaction (resetting all out bits consumes power)
	//end




endmodule

tests/cmd/test_deserializer.v
`include "src/cmd/deserializer.v"

module test_deserializer;

    reg reset = 0;
    reg enable = 1;
    wire complete;		
    reg in = 0;			//serialized input
	reg [7:0] framesize = 12;			//serialized input
	wire [135:0] out;	//deserialized data
	
	reg [135:0] input_values = 136'b1010101010101011010100100100101010100100101010101101010101010100101011010010101101101111010111010111010101010101101101010101101101010101; // test input data
	reg [5:0] counter = 0;
	
    initial begin
		$display("\n----------------------- Deserializer test -------------------------\n");
		$dumpfile("tests/vcd/test_deserializer.vcd");
		$dumpvars(0, test_deserializer);
        # 2 reset = 1;  
        # 2 reset = 0;  
		# 94 enable = 0;	//out should remain the same for 2 cycles
		$display("Enabled\n");
		# 26 reset = 1;
		# 2 $finish;    
    end

    reg clk = 0;
    always #1 clk = !clk;     
	always #2 counter = counter + 1;   //next item on array  
	always@(posedge clk) begin
		in <= input_values[counter];
	end
	
	always@(posedge complete) begin
		$display("Disabled\n");
		enable = 0;
	end
	
	deserializer des (.clk(clk), .reset(reset), .in(in), .out(out), .enable(enable), .complete(complete), .framesize(framesize));
    
	initial	$monitor("At time %t: %b, out: %b complete: %b", $time,in,out,complete);

endmodule

tests/vcd/test_deserializer.vcd
$date
	Fri Dec  9 02:19:25 2016
$end
$version
	Icarus Verilog
$end
$timescale
	1s
$end
$scope module test_deserializer $end
$var wire 1 ! complete $end
$var wire 136 " out [135:0] $end
$var reg 1 # clk $end
$var reg 6 $ counter [5:0] $end
$var reg 1 % enable $end
$var reg 8 & framesize [7:0] $end
$var reg 1 ' in $end
$var reg 136 ( input_values [135:0] $end
$var reg 1 ) reset $end
$scope module des $end
$var wire 1 * clk $end
$var wire 1 + enable $end
$var wire 8 , framesize [7:0] $end
$var wire 1 - in $end
$var wire 1 . reset $end
$var reg 1 / complete $end
$var reg 8 0 counter [7:0] $end
$var reg 136 1 out [135:0] $end
$upscope $end
$upscope $end
$enddefinitions $end
#0
$dumpvars
bx 1
bx 0
x/
0.
0-
b1011 ,
1+
0*
0)
b1010101010101011010100100100101010100100101010101101010101010100101011010010101101101111010111010111010101010101101101010101101101010101 (
0'
b1011 &
1%
b0 $
0#
bx "
x!
$end
#1
1'
1-
1#
1*
#2
0/
0!
b1011 0
b0 1
b0 "
0#
0*
b1 $
1)
1.
#3
0'
0-
b100000000000 1
b100000000000 "
b1010 0
1#
1*
#4
0#
0*
b10 $
0)
0.
#5
b100000000000 1
1'
1-
b1001 0
1#
1*
#6
0#
0*
b11 $
#7
0'
0-
b101000000000 1
b101000000000 "
b1000 0
1#
1*
#8
0#
0*
b100 $
#9
b101000000000 1
1'
1-
b111 0
1#
1*
#10
0#
0*
b101 $
#11
0'
0-
b101010000000 1
b101010000000 "
b110 0
1#
1*
#12
0#
0*
b110 $
#13
b101010000000 1
1'
1-
b101 0
1#
1*
#14
0#
0*
b111 $
#15
0'
0-
b101010100000 1
b101010100000 "
b100 0
1#
1*
#16
0#
0*
b1000 $
#17
b101010100000 1
1'
1-
b11 0
1#
1*
#18
0#
0*
b1001 $
#19
b101010101000 1
b101010101000 "
b10 0
1#
1*
#20
0#
0*
b1010 $
#21
b101010101100 1
b101010101100 "
0'
0-
b1 0
1#
1*
#22
0#
0*
b1011 $
#23
1'
1-
b101010101100 1
b0 0
1#
1*
#24
0#
0*
b1100 $
#25
b101010101101 1
b101010101101 "
0%
0+
1/
1!
b1011 0
1#
1*
#26
0#
0*
b1101 $
#27
0'
0-
0/
0!
1#
1*
#28
0#
0*
b1110 $
#29
1'
1-
1#
1*
#30
0#
0*
b1111 $
#31
0'
0-
1#
1*
#32
0#
0*
b10000 $
#33
1'
1-
1#
1*
#34
0#
0*
b10001 $
#35
0'
0-
1#
1*
#36
0#
0*
b10010 $
#37
1'
1-
1#
1*
#38
0#
0*
b10011 $
#39
0'
0-
1#
1*
#40
0#
0*
b10100 $
#41
1'
1-
1#
1*
#42
0#
0*
b10101 $
#43
1#
1*
#44
0#
0*
b10110 $
#45
0'
0-
1#
1*
#46
0#
0*
b10111 $
#47
1'
1-
1#
1*
#48
0#
0*
b11000 $
#49
1#
1*
#50
0#
0*
b11001 $
#51
0'
0-
1#
1*
#52
0#
0*
b11010 $
#53
1'
1-
1#
1*
#54
0#
0*
b11011 $
#55
0'
0-
1#
1*
#56
0#
0*
b11100 $
#57
1'
1-
1#
1*
#58
0#
0*
b11101 $
#59
0'
0-
1#
1*
#60
0#
0*
b11110 $
#61
1'
1-
1#
1*
#62
0#
0*
b11111 $
#63
0'
0-
1#
1*
#64
0#
0*
b100000 $
#65
1'
1-
1#
1*
#66
0#
0*
b100001 $
#67
0'
0-
1#
1*
#68
0#
0*
b100010 $
#69
1'
1-
1#
1*
#70
0#
0*
b100011 $
#71
0'
0-
1#
1*
#72
0#
0*
b100100 $
#73
1'
1-
1#
1*
#74
0#
0*
b100101 $
#75
1#
1*
#76
0#
0*
b100110 $
#77
1#
1*
#78
0#
0*
b100111 $
#79
0'
0-
1#
1*
#80
0#
0*
b101000 $
#81
1'
1-
1#
1*
#82
0#
0*
b101001 $
#83
0'
0-
1#
1*
#84
0#
0*
b101010 $
#85
1'
1-
1#
1*
#86
0#
0*
b101011 $
#87
1#
1*
#88
0#
0*
b101100 $
#89
1#
1*
#90
0#
0*
b101101 $
#91
0'
0-
1#
1*
#92
0#
0*
b101110 $
#93
1'
1-
1#
1*
#94
0#
0*
b101111 $
#95
0'
0-
1#
1*
#96
0#
0*
b110000 $
#97
1'
1-
1#
1*
#98
0#
0*
b110001 $
#99
1#
1*
#100
0#
0*
b110010 $
#101
1#
1*
#102
0#
0*
b110011 $
#103
1#
1*
#104
0#
0*
b110100 $
#105
0'
0-
1#
1*
#106
0#
0*
b110101 $
#107
1'
1-
1#
1*
#108
0#
0*
b110110 $
#109
1#
1*
#110
0#
0*
b110111 $
#111
0'
0-
1#
1*
#112
0#
0*
b111000 $
#113
1'
1-
1#
1*
#114
0#
0*
b111001 $
#115
1#
1*
#116
0#
0*
b111010 $
#117
0'
0-
1#
1*
#118
0#
0*
b111011 $
#119
1'
1-
1#
1*
#120
0#
0*
b111100 $
#121
0'
0-
1#
1*
#122
0#
0*
b111101 $
#123
1'
1-
1#
1*
#124
b0 1
b0 "
0#
0*
b111110 $
1)
1.
#125
0'
0-
1#
1*
#126
0#
0*
b111111 $
