src/cmd/serializer.v
module serializer(
	clk, 		//clock to send serialized data on out line
	reset, 		//reset counter to 0 on high
	in, 		//deserialized data
	out 		//serialized data
);
	
	parameter BITS = 48;		//size of serializer
	parameter BITS_COUNTER = 6;	//size of counter, must be at least log2(BITS)

	input clk, reset;
	input [BITS-1:0] in;
	
	output reg out;
	reg [BITS_COUNTER-1:0] counter;	//we need to know which array item (in) to read from
		
	always@(reset) begin
		counter = 0;
	end
	
	
	always@(posedge clk) begin
		if(enable && ~(counter==BITS)) begin	//when counter gets to limit, it'll stop counting until it's reset
			out <= in[counter];
			if(~reset) begin			//as long we're not resetting the counter
				counter = counter + 1;	//next item
			end
		end
	end
	
	
	
endmodule

tests/cmd/test_serializer.v
`include "src/cmd/serializer.v"

module test_serializer;

    reg reset = 1;
	reg [47:0] in = 48'b101011010111101011101011101010101010101001110101; // test input data
	wire out;	//serialized output
	
    initial begin
		$display("\n----------------------- Serializer test -------------------------\n");
		$display("input: %b \n", in);
		$dumpfile("tests/vcd/test_serializer.vcd");
		$dumpvars(0, test_serializer);
        # 2 reset = 0;  
		# 96 $display("finished");
		reset = 1;	//counter reset to zero, reading first item
		# 4 $finish;    
    end

    reg clk = 0;
    always #1 clk = !clk;     
	
	serializer ser (.clk(clk), .reset(reset), .in(in), .out(out));
    
	initial	$monitor("At time %t: clk: %b out: %b", $time,clk, out);

endmodule

tests/vcd/test_serializer.vcd
$date
	Mon Nov 14 12:53:27 2016
$end
$version
	Icarus Verilog
$end
$timescale
	1s
$end
$scope module test_serializer $end
$var wire 1 ! out $end
$var reg 1 " clk $end
$var reg 48 # in [47:0] $end
$var reg 1 $ reset $end
$scope module ser $end
$var wire 1 % clk $end
$var wire 48 & in [47:0] $end
$var wire 1 ' reset $end
$var reg 6 ( counter [5:0] $end
$var reg 1 ) out $end
$upscope $end
$upscope $end
$enddefinitions $end
#0
$dumpvars
x)
b0 (
1'
b101011010111101011101011101010101010101001110101 &
0%
1$
b101011010111101011101011101010101010101001110101 #
0"
x!
$end
#1
1)
1!
1"
1%
#2
0"
0%
0$
0'
#3
b1 (
1"
1%
#4
0"
0%
#5
0)
0!
b10 (
1"
1%
#6
0"
0%
#7
1)
1!
b11 (
1"
1%
#8
0"
0%
#9
0)
0!
b100 (
1"
1%
#10
0"
0%
#11
1)
1!
b101 (
1"
1%
#12
0"
0%
#13
b110 (
1"
1%
#14
0"
0%
#15
b111 (
1"
1%
#16
0"
0%
#17
0)
0!
b1000 (
1"
1%
#18
0"
0%
#19
b1001 (
1"
1%
#20
0"
0%
#21
1)
1!
b1010 (
1"
1%
#22
0"
0%
#23
0)
0!
b1011 (
1"
1%
#24
0"
0%
#25
1)
1!
b1100 (
1"
1%
#26
0"
0%
#27
0)
0!
b1101 (
1"
1%
#28
0"
0%
#29
1)
1!
b1110 (
1"
1%
#30
0"
0%
#31
0)
0!
b1111 (
1"
1%
#32
0"
0%
#33
1)
1!
b10000 (
1"
1%
#34
0"
0%
#35
0)
0!
b10001 (
1"
1%
#36
0"
0%
#37
1)
1!
b10010 (
1"
1%
#38
0"
0%
#39
0)
0!
b10011 (
1"
1%
#40
0"
0%
#41
1)
1!
b10100 (
1"
1%
#42
0"
0%
#43
0)
0!
b10101 (
1"
1%
#44
0"
0%
#45
1)
1!
b10110 (
1"
1%
#46
0"
0%
#47
0)
0!
b10111 (
1"
1%
#48
0"
0%
#49
1)
1!
b11000 (
1"
1%
#50
0"
0%
#51
b11001 (
1"
1%
#52
0"
0%
#53
b11010 (
1"
1%
#54
0"
0%
#55
0)
0!
b11011 (
1"
1%
#56
0"
0%
#57
1)
1!
b11100 (
1"
1%
#58
0"
0%
#59
0)
0!
b11101 (
1"
1%
#60
0"
0%
#61
1)
1!
b11110 (
1"
1%
#62
0"
0%
#63
b11111 (
1"
1%
#64
0"
0%
#65
b100000 (
1"
1%
#66
0"
0%
#67
0)
0!
b100001 (
1"
1%
#68
0"
0%
#69
1)
1!
b100010 (
1"
1%
#70
0"
0%
#71
0)
0!
b100011 (
1"
1%
#72
0"
0%
#73
1)
1!
b100100 (
1"
1%
#74
0"
0%
#75
b100101 (
1"
1%
#76
0"
0%
#77
b100110 (
1"
1%
#78
0"
0%
#79
b100111 (
1"
1%
#80
0"
0%
#81
0)
0!
b101000 (
1"
1%
#82
0"
0%
#83
1)
1!
b101001 (
1"
1%
#84
0"
0%
#85
0)
0!
b101010 (
1"
1%
#86
0"
0%
#87
1)
1!
b101011 (
1"
1%
#88
0"
0%
#89
b101100 (
1"
1%
#90
0"
0%
#91
0)
0!
b101101 (
1"
1%
#92
0"
0%
#93
1)
1!
b101110 (
1"
1%
#94
0"
0%
#95
0)
0!
b101111 (
1"
1%
#96
0"
0%
#97
1)
1!
b110000 (
1"
1%
#98
b0 (
0"
0%
1$
1'
