src/cmd/deserializer.v
module deserializer(
	clk, 		//serialized data proper clock
	reset, 		//set output to zero and reset counter to 0 on high
	in, 		//serialized data
	out, 		//deserialized data
	finish		//reset counter to 0 and hold out's data while high
);
	
	input clk, reset, in, finish;
	
	parameter BITS = 48;		//size of deserializer
	parameter BITS_COUNTER = 6;	//size of counter, must be at least log2(BITS)
	
	output reg [BITS-1:0] out;
	reg [BITS_COUNTER-1:0] counter;	//we need to know which array item (out) to write on
		
	always@(reset) begin
		out = 0;
		counter = 0;
	end
	
	
	always@(posedge clk) begin
		if(~finish) begin
			out[counter] <= in;
			if(~reset && ~finish) begin	//as long there's not any reset state, count
				counter = counter + 1;	//next item
			end
		end
	end
	
	always@(finish) begin
		counter = 0;
	end
	
endmodule

tests/cmd/test_deserializer.v
`include "src/cmd/deserializer.v"

module test_deserializer;

    reg reset = 1;
    reg finish = 0;		
    reg in = 0;			//serialized input
	wire [47:0] out;	//deserialized data
	
	reg [47:0] input_values = 48'b101011010111101011101011101010101010101001110100; // test input data
	reg [5:0] counter = 0;
	
    initial begin
		$display("\n----------------------- Deserializer test -------------------------\n");
		$dumpfile("tests/vcd/test_deserializer.vcd");
		$dumpvars(0, test_deserializer);
        # 2 reset = 0;  
		# 96 finish = 1;	//out should remain the same for 2 cycles
		# 4 reset = 1;
		# 2 $finish;    
    end

    reg clk = 0;
    always #1 clk = !clk;     
	always #2 counter = counter + 1;   //next item on array  
	always@(posedge clk) begin
		in <= input_values[counter];
	end
	
	deserializer des (.clk(clk), .reset(reset), .in(in), .out(out), .finish(finish));
    
    initial	$monitor("At time %t: %b, out: %b", $time,in,out);

endmodule

tests/vcd/test_deserializer.vcd
$date
	Mon Nov 14 13:01:38 2016
$end
$version
	Icarus Verilog
$end
$timescale
	1s
$end
$scope module test_deserializer $end
$var wire 48 ! out [47:0] $end
$var reg 1 " clk $end
$var reg 6 # counter [5:0] $end
$var reg 1 $ finish $end
$var reg 1 % in $end
$var reg 48 & input_values [47:0] $end
$var reg 1 ' reset $end
$scope module des $end
$var wire 1 ( clk $end
$var wire 1 ) finish $end
$var wire 1 * in $end
$var wire 1 + reset $end
$var reg 6 , counter [5:0] $end
$var reg 48 - out [47:0] $end
$upscope $end
$upscope $end
$enddefinitions $end
#0
$dumpvars
b0 -
b0 ,
1+
0*
0)
0(
1'
b101011010111101011101011101010101010101001110100 &
0%
0$
b0 #
0"
b0 !
$end
#1
b0 -
1"
1(
#2
0"
0(
b1 #
0'
0+
#3
b0 -
b1 ,
1"
1(
#4
0"
0(
b10 #
#5
b0 -
1%
1*
b10 ,
1"
1(
#6
0"
0(
b11 #
#7
0%
0*
b100 -
b100 !
b11 ,
1"
1(
#8
0"
0(
b100 #
#9
b100 -
1%
1*
b100 ,
1"
1(
#10
0"
0(
b101 #
#11
b10100 -
b10100 !
b101 ,
1"
1(
#12
0"
0(
b110 #
#13
b110100 -
b110100 !
b110 ,
1"
1(
#14
0"
0(
b111 #
#15
0%
0*
b1110100 -
b1110100 !
b111 ,
1"
1(
#16
0"
0(
b1000 #
#17
b1110100 -
b1000 ,
1"
1(
#18
0"
0(
b1001 #
#19
1%
1*
b1110100 -
b1001 ,
1"
1(
#20
0"
0(
b1010 #
#21
b1001110100 -
b1001110100 !
0%
0*
b1010 ,
1"
1(
#22
0"
0(
b1011 #
#23
1%
1*
b1001110100 -
b1011 ,
1"
1(
#24
0"
0(
b1100 #
#25
b101001110100 -
b101001110100 !
0%
0*
b1100 ,
1"
1(
#26
0"
0(
b1101 #
#27
1%
1*
b101001110100 -
b1101 ,
1"
1(
#28
0"
0(
b1110 #
#29
b10101001110100 -
b10101001110100 !
0%
0*
b1110 ,
1"
1(
#30
0"
0(
b1111 #
#31
1%
1*
b10101001110100 -
b1111 ,
1"
1(
#32
0"
0(
b10000 #
#33
b1010101001110100 -
b1010101001110100 !
0%
0*
b10000 ,
1"
1(
#34
0"
0(
b10001 #
#35
1%
1*
b1010101001110100 -
b10001 ,
1"
1(
#36
0"
0(
b10010 #
#37
b101010101001110100 -
b101010101001110100 !
0%
0*
b10010 ,
1"
1(
#38
0"
0(
b10011 #
#39
1%
1*
b101010101001110100 -
b10011 ,
1"
1(
#40
0"
0(
b10100 #
#41
b10101010101001110100 -
b10101010101001110100 !
0%
0*
b10100 ,
1"
1(
#42
0"
0(
b10101 #
#43
1%
1*
b10101010101001110100 -
b10101 ,
1"
1(
#44
0"
0(
b10110 #
#45
b1010101010101001110100 -
b1010101010101001110100 !
0%
0*
b10110 ,
1"
1(
#46
0"
0(
b10111 #
#47
1%
1*
b1010101010101001110100 -
b10111 ,
1"
1(
#48
0"
0(
b11000 #
#49
b101010101010101001110100 -
b101010101010101001110100 !
b11000 ,
1"
1(
#50
0"
0(
b11001 #
#51
b1101010101010101001110100 -
b1101010101010101001110100 !
b11001 ,
1"
1(
#52
0"
0(
b11010 #
#53
b11101010101010101001110100 -
b11101010101010101001110100 !
0%
0*
b11010 ,
1"
1(
#54
0"
0(
b11011 #
#55
1%
1*
b11101010101010101001110100 -
b11011 ,
1"
1(
#56
0"
0(
b11100 #
#57
b1011101010101010101001110100 -
b1011101010101010101001110100 !
0%
0*
b11100 ,
1"
1(
#58
0"
0(
b11101 #
#59
1%
1*
b1011101010101010101001110100 -
b11101 ,
1"
1(
#60
0"
0(
b11110 #
#61
b101011101010101010101001110100 -
b101011101010101010101001110100 !
b11110 ,
1"
1(
#62
0"
0(
b11111 #
#63
b1101011101010101010101001110100 -
b1101011101010101010101001110100 !
b11111 ,
1"
1(
#64
0"
0(
b100000 #
#65
b11101011101010101010101001110100 -
b11101011101010101010101001110100 !
0%
0*
b100000 ,
1"
1(
#66
0"
0(
b100001 #
#67
1%
1*
b11101011101010101010101001110100 -
b100001 ,
1"
1(
#68
0"
0(
b100010 #
#69
b1011101011101010101010101001110100 -
b1011101011101010101010101001110100 !
0%
0*
b100010 ,
1"
1(
#70
0"
0(
b100011 #
#71
1%
1*
b1011101011101010101010101001110100 -
b100011 ,
1"
1(
#72
0"
0(
b100100 #
#73
b101011101011101010101010101001110100 -
b101011101011101010101010101001110100 !
b100100 ,
1"
1(
#74
0"
0(
b100101 #
#75
b1101011101011101010101010101001110100 -
b1101011101011101010101010101001110100 !
b100101 ,
1"
1(
#76
0"
0(
b100110 #
#77
b11101011101011101010101010101001110100 -
b11101011101011101010101010101001110100 !
b100110 ,
1"
1(
#78
0"
0(
b100111 #
#79
0%
0*
b111101011101011101010101010101001110100 -
b111101011101011101010101010101001110100 !
b100111 ,
1"
1(
#80
0"
0(
b101000 #
#81
b111101011101011101010101010101001110100 -
1%
1*
b101000 ,
1"
1(
#82
0"
0(
b101001 #
#83
0%
0*
b10111101011101011101010101010101001110100 -
b10111101011101011101010101010101001110100 !
b101001 ,
1"
1(
#84
0"
0(
b101010 #
#85
b10111101011101011101010101010101001110100 -
1%
1*
b101010 ,
1"
1(
#86
0"
0(
b101011 #
#87
b1010111101011101011101010101010101001110100 -
b1010111101011101011101010101010101001110100 !
b101011 ,
1"
1(
#88
0"
0(
b101100 #
#89
b11010111101011101011101010101010101001110100 -
b11010111101011101011101010101010101001110100 !
0%
0*
b101100 ,
1"
1(
#90
0"
0(
b101101 #
#91
1%
1*
b11010111101011101011101010101010101001110100 -
b101101 ,
1"
1(
#92
0"
0(
b101110 #
#93
b1011010111101011101011101010101010101001110100 -
b1011010111101011101011101010101010101001110100 !
0%
0*
b101110 ,
1"
1(
#94
0"
0(
b101111 #
#95
1%
1*
b1011010111101011101011101010101010101001110100 -
b101111 ,
1"
1(
#96
0"
0(
b110000 #
#97
b101011010111101011101011101010101010101001110100 -
b101011010111101011101011101010101010101001110100 !
x%
x*
b110000 ,
1"
1(
#98
b0 ,
0"
0(
b110001 #
1$
1)
#99
1"
1(
#100
0"
0(
b110010 #
#101
1"
1(
#102
b0 -
b0 !
0"
0(
b110011 #
1'
1+
#103
1"
1(
#104
0"
0(
b110100 #
